blexy/__init__.py
blexy/app.py
blexy/main.py
blexy/devices/LYWSD03MMC.py
blexy/devices/__init__.py
blexy/devices/abstract_device.py
blexy/utils/__init__.py
blexy/utils/concurrency.py
blexy/utils/config.py
blexy/utils/openmetrics.py
blexy-0.2.0.dist-info/LICENSE
blexy-0.2.0.dist-info/METADATA
blexy-0.2.0.dist-info/WHEEL
blexy-0.2.0.dist-info/entry_points.txt
blexy-0.2.0.dist-info/top_level.txt
blexy-0.2.0.dist-info/RECORD
