Metadata-Version: 2.1
Name: blexy
Version: 0.2.0
Summary: Simple OpenMetrics exporter for BLE devices
Home-page: https://github.com/rostrovsky/blexy
License: MIT
Keywords: ble openmetrics bluetooth prometheus raspberry pi iot sensors
Platform: UNKNOWN
Classifier: Development Status :: 3 - Alpha
Classifier: Intended Audience :: Developers
Classifier: License :: OSI Approved :: MIT License
Classifier: Programming Language :: Python :: 3
Classifier: Programming Language :: Python :: 3.7
Classifier: Programming Language :: Python :: 3.8
Classifier: Programming Language :: Python :: 3.9
Requires-Python: >=3.7
License-File: LICENSE
Requires-Dist: click
Requires-Dist: starlette
Requires-Dist: pyyaml
Requires-Dist: uvicorn
Requires-Dist: bluepy
Requires-Dist: twiggy
